icolyzer/__init__.py
icolyzer/analyzer.py
icolyzer/cli.py
icolyzer/converter.py
icolyzer/plotter.py
icolyzer/iftlibrary/__init__.py
icolyzer/iftlibrary/ift.py
icolyzer/iftlibrary/lib/ift.dll
icolyzer/iftlibrary/lib/libift-arm64.so
icolyzer/iftlibrary/lib/libift-armv7l.so
icolyzer/iftlibrary/lib/libift-x64.so
icolyzer/iftlibrary/lib/libift.dylib
icolyzer-1.8.0.dist-info/METADATA
icolyzer-1.8.0.dist-info/WHEEL
icolyzer-1.8.0.dist-info/entry_points.txt
icolyzer-1.8.0.dist-info/top_level.txt
icolyzer-1.8.0.dist-info/RECORD
