Metadata-Version: 2.1
Name: icolyzer
Version: 1.8.0
Summary: Auxiliary set of tools to work with measurement data produced by the ICOtronic system
Author-email: Clemens Burgstaller <burgstaller@ift.at>, Norbert Leder <norbert.leder@mytoolit.com>, René Schwaiger <rene.schwaiger@ift.at>, Thomas Hirschbüchler <hirschbuechler@ift.at>
Project-URL: Source, https://github.com/mytoolit/ICOlyzer/
Keywords: smart-tool,smh,stu,sth,tool-holder
Classifier: Development Status :: 3 - Alpha
Classifier: License :: Other/Proprietary License
Classifier: Natural Language :: English
Classifier: Operating System :: MacOS
Classifier: Operating System :: POSIX :: Linux
Classifier: Operating System :: Microsoft :: Windows
Classifier: Programming Language :: Python
Requires-Python: >=3.10
Requires-Dist: matplotlib >=3.5.1
Requires-Dist: numpy >=1.20
Requires-Dist: pandas >=1.3.5
Requires-Dist: tables <4,>=3.10.1
Requires-Dist: openpyxl
Requires-Dist: rich >=13.4.1
Provides-Extra: dev
Requires-Dist: flake8 ; extra == 'dev'
Requires-Dist: mypy ; extra == 'dev'
Requires-Dist: pylint >=3.0.2 ; extra == 'dev'
Requires-Dist: toml ; extra == 'dev'
Provides-Extra: test
Requires-Dist: prysk[pytest-plugin] >=0.13.1 ; extra == 'test'
Requires-Dist: pytest ; extra == 'test'
